pypi_api_installer/__init__.py
pypi_api_installer/tools/__init__.py
pypi_api_installer/tools/check_library_exist.py
pypi_api_installer/tools/get_all_library_releases.py
pypi_api_installer/tools/get_dependencies.py
pypi_api_installer/tools/install_library.py
pypi_api_installer/tools/is_user_have_library.py
pypi_api_installer/tools/magic_library_installer.py
pypi_api_installer/tools/uncompress_library.py
pypi_api_installer/utils/__init__.py
pypi_api_installer/utils/parse_package_string.py
pypi_api_installer-1.4.dist-info/LICENSE
pypi_api_installer-1.4.dist-info/METADATA
pypi_api_installer-1.4.dist-info/WHEEL
pypi_api_installer-1.4.dist-info/top_level.txt
pypi_api_installer-1.4.dist-info/RECORD
