Metadata-Version: 2.1
Name: pypi_api_installer
Version: 1.4
Summary: A python library with a set of tools for installing packages from pypi dynamically
Home-page: https://github.com/SKbarbon/pypi_api_installer
Author: SKbarbon
Classifier: Programming Language :: Python :: 3
Classifier: Operating System :: MacOS :: MacOS X
Classifier: Operating System :: Microsoft :: Windows
License-File: LICENSE
Requires-Dist: requests
